LICENSE
MANIFEST.in
README.md
pyproject.toml
setup.json
setup.py
aiida_statefile_schedulers/__init__.py
aiida_statefile_schedulers.egg-info/PKG-INFO
aiida_statefile_schedulers.egg-info/SOURCES.txt
aiida_statefile_schedulers.egg-info/dependency_links.txt
aiida_statefile_schedulers.egg-info/entry_points.txt
aiida_statefile_schedulers.egg-info/requires.txt
aiida_statefile_schedulers.egg-info/top_level.txt