Metadata-Version: 2.1
Name: aiida-statefile-schedulers
Version: 0.2.1
Summary: Simple statefile-driven task schedulers for AiiDA
Home-page: https://github.com/dev-zero/aiida-statefile-schedulers
Author: Tiziano Müller
Author-email: tm@dev-zero.ch
License: MIT
Platform: UNKNOWN
Classifier: Programming Language :: Python
Classifier: Intended Audience :: Science/Research
Classifier: License :: OSI Approved :: MIT License
Classifier: Natural Language :: English
Classifier: Framework :: AiiDA
Provides-Extra: testing
Provides-Extra: pre-commit
License-File: LICENSE
